qtools/__init__.py
qtools/rand.py
qtools/values.py
qtools/writing.py
quantung_tools-0.0.1.dist-info/licenses/LICENSE
quantung_tools-0.0.1.dist-info/METADATA
quantung_tools-0.0.1.dist-info/WHEEL
quantung_tools-0.0.1.dist-info/top_level.txt
quantung_tools-0.0.1.dist-info/RECORD
